kontol/__init__.py
kontol/cli.py
kontol/clis/__init__.py
kontol/clis/base.py
kontol/clis/masukin.py
kontol-1.0.3.dist-info/DESCRIPTION.rst
kontol-1.0.3.dist-info/METADATA
kontol-1.0.3.dist-info/RECORD
kontol-1.0.3.dist-info/WHEEL
kontol-1.0.3.dist-info/entry_points.txt
kontol-1.0.3.dist-info/metadata.json
kontol-1.0.3.dist-info/top_level.txt
